{
    "os": "Linux-5.4.0-131-generic-x86_64-with-glibc2.29",
    "python": "3.8.10",
    "heartbeatAt": "2024-01-25T18:40:38.509857",
    "startedAt": "2024-01-25T18:40:37.938480",
    "docker": null,
    "cuda": null,
    "args": [],
    "state": "running",
    "program": "dsep_trials.py",
    "codePathLocal": "dsep_trials.py",
    "codePath": "dsep_trials.py",
    "git": {
        "remote": "https://github.com/Shailen24/personal_hlab",
        "commit": "0f35e14ceec025a7c0076408f8dc8ff2d9628b9a"
    },
    "email": null,
    "root": "/home/ssmith/autoencoder_hulm",
    "host": "cronus",
    "username": "ssmith",
    "executable": "/usr/bin/python3",
    "cpu_count": 24,
    "cpu_count_logical": 48,
    "cpu_freq": {
        "current": 1334.76725,
        "min": 800.0,
        "max": 3300.0
    },
    "cpu_freq_per_core": [
        {
            "current": 2700.101,
            "min": 800.0,
            "max": 3300.0
        },
        {
            "current": 799.798,
            "min": 800.0,
            "max": 3300.0
        },
        {
            "current": 799.778,
            "min": 800.0,
            "max": 3300.0
        },
        {
            "current": 799.928,
            "min": 800.0,
            "max": 3300.0
        },
        {
            "current": 799.031,
            "min": 800.0,
            "max": 3300.0
        },
        {
            "current": 1049.632,
            "min": 800.0,
            "max": 3300.0
        },
        {
            "current": 2700.427,
            "min": 800.0,
            "max": 3300.0
        },
        {
            "current": 800.017,
            "min": 800.0,
            "max": 3300.0
        },
        {
            "current": 2700.0,
            "min": 800.0,
            "max": 3300.0
        },
        {
            "current": 800.006,
            "min": 800.0,
            "max": 3300.0
        },
        {
            "current": 800.015,
            "min": 800.0,
            "max": 3300.0
        },
        {
            "current": 799.998,
            "min": 800.0,
            "max": 3300.0
        },
        {
            "current": 800.473,
            "min": 800.0,
            "max": 3300.0
        },
        {
            "current": 799.097,
            "min": 800.0,
            "max": 3300.0
        },
        {
            "current": 800.535,
            "min": 800.0,
            "max": 3300.0
        },
        {
            "current": 800.504,
            "min": 800.0,
            "max": 3300.0
        },
        {
            "current": 800.106,
            "min": 800.0,
            "max": 3300.0
        },
        {
            "current": 800.576,
            "min": 800.0,
            "max": 3300.0
        },
        {
            "current": 2696.931,
            "min": 800.0,
            "max": 3300.0
        },
        {
            "current": 800.0,
            "min": 800.0,
            "max": 3300.0
        },
        {
            "current": 800.0,
            "min": 800.0,
            "max": 3300.0
        },
        {
            "current": 2696.687,
            "min": 800.0,
            "max": 3300.0
        },
        {
            "current": 2700.0,
            "min": 800.0,
            "max": 3300.0
        },
        {
            "current": 2100.0,
            "min": 800.0,
            "max": 3300.0
        },
        {
            "current": 2700.0,
            "min": 800.0,
            "max": 3300.0
        },
        {
            "current": 800.33,
            "min": 800.0,
            "max": 3300.0
        },
        {
            "current": 800.973,
            "min": 800.0,
            "max": 3300.0
        },
        {
            "current": 800.0,
            "min": 800.0,
            "max": 3300.0
        },
        {
            "current": 800.0,
            "min": 800.0,
            "max": 3300.0
        },
        {
            "current": 876.768,
            "min": 800.0,
            "max": 3300.0
        },
        {
            "current": 2700.002,
            "min": 800.0,
            "max": 3300.0
        },
        {
            "current": 800.064,
            "min": 800.0,
            "max": 3300.0
        },
        {
            "current": 2703.708,
            "min": 800.0,
            "max": 3300.0
        },
        {
            "current": 800.0,
            "min": 800.0,
            "max": 3300.0
        },
        {
            "current": 799.04,
            "min": 800.0,
            "max": 3300.0
        },
        {
            "current": 800.889,
            "min": 800.0,
            "max": 3300.0
        },
        {
            "current": 801.048,
            "min": 800.0,
            "max": 3300.0
        },
        {
            "current": 800.25,
            "min": 800.0,
            "max": 3300.0
        },
        {
            "current": 800.157,
            "min": 800.0,
            "max": 3300.0
        },
        {
            "current": 801.104,
            "min": 800.0,
            "max": 3300.0
        },
        {
            "current": 800.0,
            "min": 800.0,
            "max": 3300.0
        },
        {
            "current": 800.813,
            "min": 800.0,
            "max": 3300.0
        },
        {
            "current": 2704.732,
            "min": 800.0,
            "max": 3300.0
        },
        {
            "current": 799.105,
            "min": 800.0,
            "max": 3300.0
        },
        {
            "current": 800.186,
            "min": 800.0,
            "max": 3300.0
        },
        {
            "current": 2704.025,
            "min": 800.0,
            "max": 3300.0
        },
        {
            "current": 2704.028,
            "min": 800.0,
            "max": 3300.0
        },
        {
            "current": 2099.524,
            "min": 800.0,
            "max": 3300.0
        }
    ],
    "disk": {
        "/": {
            "total": 428.07342529296875,
            "used": 284.1254119873047
        }
    },
    "gpu": "NVIDIA RTX A6000",
    "gpu_count": 4,
    "gpu_devices": [
        {
            "name": "NVIDIA RTX A6000",
            "memory_total": 51527024640
        },
        {
            "name": "NVIDIA RTX A6000",
            "memory_total": 51527024640
        },
        {
            "name": "NVIDIA RTX A6000",
            "memory_total": 51527024640
        },
        {
            "name": "NVIDIA RTX A6000",
            "memory_total": 51527024640
        }
    ],
    "memory": {
        "total": 1007.5453834533691
    }
}
