{
    "os": "Linux-5.4.0-131-generic-x86_64-with-glibc2.29",
    "python": "3.8.10",
    "heartbeatAt": "2024-01-24T04:49:22.761372",
    "startedAt": "2024-01-24T04:49:22.210679",
    "docker": null,
    "cuda": null,
    "args": [],
    "state": "running",
    "program": "rev_trials.py",
    "codePathLocal": "rev_trials.py",
    "codePath": "rev_trials.py",
    "git": {
        "remote": "https://github.com/Shailen24/personal_hlab",
        "commit": "0f35e14ceec025a7c0076408f8dc8ff2d9628b9a"
    },
    "email": null,
    "root": "/home/ssmith/autoencoder_hulm",
    "host": "cronus",
    "username": "ssmith",
    "executable": "/usr/bin/python3",
    "cpu_count": 24,
    "cpu_count_logical": 48,
    "cpu_freq": {
        "current": 2494.3409375,
        "min": 800.0,
        "max": 3300.0
    },
    "cpu_freq_per_core": [
        {
            "current": 2463.663,
            "min": 800.0,
            "max": 3300.0
        },
        {
            "current": 2464.42,
            "min": 800.0,
            "max": 3300.0
        },
        {
            "current": 2455.978,
            "min": 800.0,
            "max": 3300.0
        },
        {
            "current": 2463.193,
            "min": 800.0,
            "max": 3300.0
        },
        {
            "current": 2463.136,
            "min": 800.0,
            "max": 3300.0
        },
        {
            "current": 2462.949,
            "min": 800.0,
            "max": 3300.0
        },
        {
            "current": 2462.879,
            "min": 800.0,
            "max": 3300.0
        },
        {
            "current": 2492.761,
            "min": 800.0,
            "max": 3300.0
        },
        {
            "current": 2462.6,
            "min": 800.0,
            "max": 3300.0
        },
        {
            "current": 2447.218,
            "min": 800.0,
            "max": 3300.0
        },
        {
            "current": 2462.324,
            "min": 800.0,
            "max": 3300.0
        },
        {
            "current": 2476.119,
            "min": 800.0,
            "max": 3300.0
        },
        {
            "current": 2526.856,
            "min": 800.0,
            "max": 3300.0
        },
        {
            "current": 2500.0,
            "min": 800.0,
            "max": 3300.0
        },
        {
            "current": 2500.207,
            "min": 800.0,
            "max": 3300.0
        },
        {
            "current": 2500.0,
            "min": 800.0,
            "max": 3300.0
        },
        {
            "current": 2527.194,
            "min": 800.0,
            "max": 3300.0
        },
        {
            "current": 2485.554,
            "min": 800.0,
            "max": 3300.0
        },
        {
            "current": 2527.344,
            "min": 800.0,
            "max": 3300.0
        },
        {
            "current": 2527.493,
            "min": 800.0,
            "max": 3300.0
        },
        {
            "current": 2545.18,
            "min": 800.0,
            "max": 3300.0
        },
        {
            "current": 2545.646,
            "min": 800.0,
            "max": 3300.0
        },
        {
            "current": 2538.744,
            "min": 800.0,
            "max": 3300.0
        },
        {
            "current": 2550.894,
            "min": 800.0,
            "max": 3300.0
        },
        {
            "current": 2460.095,
            "min": 800.0,
            "max": 3300.0
        },
        {
            "current": 2459.895,
            "min": 800.0,
            "max": 3300.0
        },
        {
            "current": 2459.814,
            "min": 800.0,
            "max": 3300.0
        },
        {
            "current": 2490.777,
            "min": 800.0,
            "max": 3300.0
        },
        {
            "current": 2459.506,
            "min": 800.0,
            "max": 3300.0
        },
        {
            "current": 2481.376,
            "min": 800.0,
            "max": 3300.0
        },
        {
            "current": 2480.5,
            "min": 800.0,
            "max": 3300.0
        },
        {
            "current": 2458.96,
            "min": 800.0,
            "max": 3300.0
        },
        {
            "current": 2478.978,
            "min": 800.0,
            "max": 3300.0
        },
        {
            "current": 2458.646,
            "min": 800.0,
            "max": 3300.0
        },
        {
            "current": 2467.298,
            "min": 800.0,
            "max": 3300.0
        },
        {
            "current": 2458.325,
            "min": 800.0,
            "max": 3300.0
        },
        {
            "current": 2527.512,
            "min": 800.0,
            "max": 3300.0
        },
        {
            "current": 2527.669,
            "min": 800.0,
            "max": 3300.0
        },
        {
            "current": 2527.74,
            "min": 800.0,
            "max": 3300.0
        },
        {
            "current": 2527.901,
            "min": 800.0,
            "max": 3300.0
        },
        {
            "current": 2527.974,
            "min": 800.0,
            "max": 3300.0
        },
        {
            "current": 2528.141,
            "min": 800.0,
            "max": 3300.0
        },
        {
            "current": 2528.216,
            "min": 800.0,
            "max": 3300.0
        },
        {
            "current": 2503.506,
            "min": 800.0,
            "max": 3300.0
        },
        {
            "current": 2528.48,
            "min": 800.0,
            "max": 3300.0
        },
        {
            "current": 2528.644,
            "min": 800.0,
            "max": 3300.0
        },
        {
            "current": 2528.713,
            "min": 800.0,
            "max": 3300.0
        },
        {
            "current": 2528.884,
            "min": 800.0,
            "max": 3300.0
        }
    ],
    "disk": {
        "/": {
            "total": 428.07342529296875,
            "used": 284.24314880371094
        }
    },
    "gpu": "NVIDIA RTX A6000",
    "gpu_count": 4,
    "gpu_devices": [
        {
            "name": "NVIDIA RTX A6000",
            "memory_total": 51527024640
        },
        {
            "name": "NVIDIA RTX A6000",
            "memory_total": 51527024640
        },
        {
            "name": "NVIDIA RTX A6000",
            "memory_total": 51527024640
        },
        {
            "name": "NVIDIA RTX A6000",
            "memory_total": 51527024640
        }
    ],
    "memory": {
        "total": 1007.5453834533691
    }
}
